edith/__init__.py
edith/artifact_store.py
edith/artifact_utils.py
edith/base_client.py
edith/callbacks.py
edith/device_utils.py
edith/exceptions.py
edith/experiment.py
edith/nlp_client.py
edith/session.py
edith/trial.py
edith/utils.py
edith_sdk-0.1.1.dist-info/LICENSE
edith_sdk-0.1.1.dist-info/METADATA
edith_sdk-0.1.1.dist-info/WHEEL
edith_sdk-0.1.1.dist-info/top_level.txt
edith_sdk-0.1.1.dist-info/RECORD
